{
  "id": "0009g",
  "source_workbook": "kalshi-price-history-kxatpchallengermatch-26feb16kozmcc-minute.xlsx",
  "event_ticker": "KXATPCHALLENGERMATCH-26FEB16KOZMCC",
  "kalshi_date": "2026-02-16",
  "player_name": "Tristan McCormick",
  "opponent_name": "Stefan Kozlov",
  "player_side": "dog",
  "match_winner": "Stefan Kozlov",
  "final_score": "6-3 6-7(4) 6-4",
  "starting_price": 9.0,
  "ending_price": 1.0,
  "min_price": 1.0,
  "max_price": 38.81,
  "opponent_starting_price": 88.0,
  "opponent_ending_price": 99.0,
  "row_count": 196,
  "trimmed_opening_rows": 2,
  "trimmed_ending_rows": 5,
  "start_timestamp": "2026-02-16T10:56:00+00:00",
  "end_timestamp": "2026-02-16T23:07:00+00:00",
  "files": {
    "csv": "0009g.csv",
    "json": "0009g.json",
    "npy": "0009g.npy"
  },
  "tags": [
    "3_sets",
    "crossed_10",
    "crossed_20",
    "crossed_25",
    "crossed_30",
    "ending_bucket_00_09",
    "ending_price_0001",
    "failed_spike",
    "first_set_loser",
    "heavy_underdog",
    "highly_oscillating_shape",
    "inverted_v_failed_spike",
    "loser",
    "many_reversals",
    "medium_range",
    "medium_single_move",
    "medium_volatility",
    "multi_crossed_10",
    "multi_crossed_20",
    "multi_crossed_25",
    "multi_crossed_30",
    "never_crossed_50",
    "opponent_stefan_kozlov",
    "player_tristan_mccormick",
    "resolved_near_0",
    "second_set_winner",
    "set_1_no_tiebreaker",
    "set_2_tiebreaker",
    "set_3_no_tiebreaker",
    "sideways_finish",
    "starting_bucket_00_09",
    "starting_price_0009",
    "third_set_loser",
    "three_set_match",
    "tiebreaker"
  ],
  "volatility_score": 1.8072,
  "max_single_move": 13.39,
  "direction_flips": 47,
  "range_points": 37.81,
  "crossings_25": 16,
  "crossings_50": 0,
  "crossings_75": 0,
  "first_cross_50_pct": ""
}