{
  "id": "0011q",
  "source_workbook": "kalshi-price-history-kxatpmatch-26mar20damzve-minute.xlsx",
  "event_ticker": "KXATPMATCH-26MAR20DAMZVE",
  "kalshi_date": "2026-03-20",
  "player_name": "Martin Damm Jr",
  "opponent_name": "Alexander Zverev",
  "player_side": "fav",
  "match_winner": "Alexander Zverev",
  "final_score": "6-2 6-4",
  "starting_price": 11.0,
  "ending_price": 1.0,
  "min_price": 1.0,
  "max_price": 11.0,
  "opponent_starting_price": 91.0,
  "opponent_ending_price": 99.0,
  "row_count": 219,
  "trimmed_opening_rows": 9,
  "trimmed_ending_rows": 8,
  "start_timestamp": "2026-03-21T15:06:00+00:00",
  "end_timestamp": "2026-03-22T02:27:00+00:00",
  "files": {
    "csv": "0011q.csv",
    "json": "0011q.json",
    "npy": "0011q.npy"
  },
  "tags": [
    "2_sets",
    "crossed_10",
    "ending_bucket_00_09",
    "ending_price_0001",
    "first_set_loser",
    "heavy_underdog",
    "highly_oscillating_shape",
    "loser",
    "low_volatility",
    "many_reversals",
    "multi_crossed_10",
    "never_crossed_50",
    "no_tiebreaker",
    "opponent_alexander_zverev",
    "player_martin_damm_jr",
    "resolved_near_0",
    "second_set_loser",
    "set_1_no_tiebreaker",
    "set_2_no_tiebreaker",
    "sideways_finish",
    "small_range",
    "small_single_move",
    "starting_bucket_10_19",
    "starting_price_0011",
    "straight_sets",
    "third_set_unknown"
  ],
  "volatility_score": 0.2842,
  "max_single_move": 4.3,
  "direction_flips": 20,
  "range_points": 10.0,
  "crossings_25": 0,
  "crossings_50": 0,
  "crossings_75": 0,
  "first_cross_50_pct": ""
}