{
  "id": "0017o",
  "source_workbook": "kalshi-price-history-kxatpchallengermatch-26jun04truhsu-minute.xlsx",
  "event_ticker": "KXATPCHALLENGERMATCH-26JUN04TRUHSU",
  "kalshi_date": "2026-06-04",
  "player_name": "Yu Hsiou Hsu",
  "opponent_name": "Marco Trungelliti",
  "player_side": "dog",
  "match_winner": "Marco Trungelliti",
  "final_score": "3-6 6-1 6-1",
  "starting_price": 17.0,
  "ending_price": 1.0,
  "min_price": 1.0,
  "max_price": 66.56,
  "opponent_starting_price": 84.0,
  "opponent_ending_price": 99.0,
  "row_count": 138,
  "trimmed_opening_rows": 4,
  "trimmed_ending_rows": 2,
  "start_timestamp": "2026-06-04T04:35:00+00:00",
  "end_timestamp": "2026-06-04T13:59:00+00:00",
  "files": {
    "csv": "0017o.csv",
    "json": "0017o.json",
    "npy": "0017o.npy"
  },
  "tags": [
    "3_sets",
    "crossed_10",
    "crossed_20",
    "crossed_25",
    "crossed_30",
    "crossed_40",
    "crossed_50",
    "crossed_60",
    "ending_bucket_00_09",
    "ending_price_0001",
    "failed_spike",
    "first_set_winner",
    "heavy_underdog",
    "highly_oscillating_shape",
    "huge_range",
    "inverted_v_failed_spike",
    "large_range",
    "loser",
    "many_reversals",
    "medium_single_move",
    "medium_volatility",
    "middle_cross_50",
    "multi_crossed_30",
    "multi_crossed_40",
    "multi_crossed_50",
    "no_tiebreaker",
    "opponent_marco_trungelliti",
    "player_yu_hsiou_hsu",
    "resolved_near_0",
    "second_set_loser",
    "set_1_no_tiebreaker",
    "set_2_no_tiebreaker",
    "set_3_no_tiebreaker",
    "sideways_finish",
    "starting_bucket_10_19",
    "starting_price_0017",
    "third_set_loser",
    "three_set_match"
  ],
  "volatility_score": 1.6143,
  "max_single_move": 8.88,
  "direction_flips": 21,
  "range_points": 65.56,
  "crossings_25": 2,
  "crossings_50": 6,
  "crossings_75": 0,
  "first_cross_50_pct": 45.99
}