{
  "id": "0018f",
  "source_workbook": "kalshi-price-history-kxatpchallengermatch-26feb24huacra-minute.xlsx",
  "event_ticker": "KXATPCHALLENGERMATCH-26FEB24HUACRA",
  "kalshi_date": "2026-02-24",
  "player_name": "Tsung-Hao Huang",
  "opponent_name": "Oliver Crawford",
  "player_side": "fav",
  "match_winner": "Oliver Crawford",
  "final_score": "6-2 4-6 6-0",
  "starting_price": 18.0,
  "ending_price": 1.0,
  "min_price": 1.0,
  "max_price": 38.51,
  "opponent_starting_price": 86.0,
  "opponent_ending_price": 99.0,
  "row_count": 237,
  "trimmed_opening_rows": 0,
  "trimmed_ending_rows": 1,
  "start_timestamp": "2026-02-24T04:08:00+00:00",
  "end_timestamp": "2026-02-24T12:07:00+00:00",
  "files": {
    "csv": "0018f.csv",
    "json": "0018f.json",
    "npy": "0018f.npy",
    "png": "png charts/0018f.png"
  },
  "tags": [
    "3_sets",
    "crossed_10",
    "crossed_20",
    "crossed_25",
    "crossed_30",
    "ending_bucket_00_09",
    "ending_price_0001",
    "first_set_loser",
    "heavy_underdog",
    "highly_oscillating_shape",
    "inverted_v_failed_spike",
    "loser",
    "many_reversals",
    "medium_range",
    "medium_single_move",
    "medium_volatility",
    "multi_crossed_10",
    "multi_crossed_25",
    "multi_crossed_30",
    "never_crossed_50",
    "no_tiebreaker",
    "opponent_oliver_crawford",
    "player_tsung_hao_huang",
    "resolved_near_0",
    "second_set_winner",
    "set_1_no_tiebreaker",
    "set_2_no_tiebreaker",
    "set_3_no_tiebreaker",
    "sideways_finish",
    "starting_bucket_10_19",
    "starting_price_0018",
    "third_set_loser",
    "three_set_match",
    "price_move_down",
    "negative_price_move",
    "price_move_down_10",
    "move_down_10",
    "minus_10_down",
    "price_contraction",
    "favorite_down_underdog_up"
  ],
  "volatility_score": 1.0269,
  "max_single_move": 13.06,
  "direction_flips": 53,
  "range_points": 37.51,
  "crossings_25": 4,
  "crossings_50": 0,
  "crossings_75": 0,
  "first_cross_50_pct": "",
  "price_move": -17.0,
  "abs_price_move": 17.0,
  "favorite_starting_price": 18.0,
  "favorite_ending_price": 1.0,
  "underdog_starting_price": 86.0,
  "underdog_ending_price": 99.0,
  "favorite_price_move": -17.0,
  "underdog_price_move": 13.0,
  "price_expansion": false,
  "price_contraction": true,
  "png_file": "png charts/0018f.png"
}