{
  "id": "0022p",
  "source_workbook": "kalshi-price-history-kxatpchallengermatch-26mar10valvil-minute.xlsx",
  "event_ticker": "KXATPCHALLENGERMATCH-26MAR10VALVIL",
  "kalshi_date": "2026-03-10",
  "player_name": "Gonzalo Villanueva",
  "opponent_name": "Adolfo Daniel Vallejo",
  "player_side": "dog",
  "match_winner": "Adolfo Daniel Vallejo",
  "final_score": "6-3 6-4",
  "starting_price": 22.0,
  "ending_price": 2.0,
  "min_price": 1.05,
  "max_price": 32.0,
  "opponent_starting_price": 81.0,
  "opponent_ending_price": 99.0,
  "row_count": 174,
  "trimmed_opening_rows": 0,
  "trimmed_ending_rows": 1,
  "start_timestamp": "2026-03-10T06:51:00+00:00",
  "end_timestamp": "2026-03-10T19:27:00+00:00",
  "files": {
    "csv": "0022p.csv",
    "json": "0022p.json",
    "npy": "0022p.npy"
  },
  "tags": [
    "2_sets",
    "crossed_10",
    "crossed_20",
    "crossed_25",
    "crossed_30",
    "ending_bucket_00_09",
    "ending_price_0002",
    "first_set_loser",
    "heavy_underdog",
    "highly_oscillating_shape",
    "loser",
    "many_reversals",
    "medium_range",
    "medium_single_move",
    "medium_volatility",
    "multi_crossed_10",
    "multi_crossed_20",
    "multi_crossed_25",
    "multi_crossed_30",
    "never_crossed_50",
    "no_tiebreaker",
    "opponent_adolfo_daniel_vallejo",
    "player_gonzalo_villanueva",
    "resolved_near_0",
    "second_set_loser",
    "set_1_no_tiebreaker",
    "set_2_no_tiebreaker",
    "sideways_finish",
    "starting_bucket_20_29",
    "starting_price_0022",
    "straight_sets",
    "third_set_unknown"
  ],
  "volatility_score": 1.0684,
  "max_single_move": 9.17,
  "direction_flips": 49,
  "range_points": 30.95,
  "crossings_25": 4,
  "crossings_50": 0,
  "crossings_75": 0,
  "first_cross_50_pct": ""
}