{
  "id": "0031cv",
  "source_workbook": "kalshi-price-history-kxatpmatch-26feb27rubgri-minute.xlsx",
  "event_ticker": "KXATPMATCH-26FEB27RUBGRI",
  "kalshi_date": "2026-02-27",
  "player_name": "Tallon Griekspoor",
  "opponent_name": "Andrey Rublev",
  "player_side": "dog",
  "match_winner": "Tallon Griekspoor",
  "final_score": "7-5 7-6(6)",
  "starting_price": 31.0,
  "ending_price": 99.0,
  "min_price": 18.24,
  "max_price": 99.0,
  "opponent_starting_price": 71.0,
  "opponent_ending_price": 1.0,
  "row_count": 448,
  "trimmed_opening_rows": 10,
  "trimmed_ending_rows": 3,
  "start_timestamp": "2026-02-27T03:59:00+00:00",
  "end_timestamp": "2026-02-27T17:01:00+00:00",
  "files": {
    "csv": "0031cv.csv",
    "json": "0031cv.json",
    "npy": "0031cv.npy",
    "png": "png charts/0031cv.png"
  },
  "tags": [
    "2_sets",
    "crossed_20",
    "crossed_25",
    "crossed_30",
    "crossed_40",
    "crossed_50",
    "crossed_60",
    "crossed_70",
    "crossed_75",
    "crossed_80",
    "crossed_90",
    "ending_bucket_90_99",
    "ending_price_0099",
    "extreme_range",
    "first_set_winner",
    "highly_oscillating_shape",
    "huge_range",
    "huge_single_move",
    "late_cross_50",
    "low_volatility",
    "many_reversals",
    "multi_crossed_25",
    "multi_crossed_30",
    "multi_crossed_40",
    "multi_crossed_50",
    "opponent_andrey_rublev",
    "player_tallon_griekspoor",
    "resolved_near_100",
    "second_set_winner",
    "set_1_no_tiebreaker",
    "set_2_tiebreaker",
    "starting_bucket_30_39",
    "starting_price_0031",
    "straight_sets",
    "third_set_unknown",
    "tiebreaker",
    "underdog",
    "uptrend_finish",
    "winner",
    "price_move_up",
    "positive_price_move",
    "price_move_up_10",
    "move_up_10",
    "plus_10_up",
    "price_move_up_20",
    "move_up_20",
    "plus_20_up",
    "price_move_up_30",
    "move_up_30",
    "plus_30_up",
    "price_move_up_40",
    "move_up_40",
    "plus_40_up",
    "price_move_up_50",
    "move_up_50",
    "plus_50_up",
    "price_move_up_60",
    "move_up_60",
    "plus_60_up",
    "price_contraction",
    "favorite_down_underdog_up"
  ],
  "volatility_score": 0.9007,
  "max_single_move": 38.74,
  "direction_flips": 55,
  "range_points": 80.76,
  "crossings_25": 4,
  "crossings_50": 3,
  "crossings_75": 1,
  "first_cross_50_pct": 96.64,
  "price_move": 68.0,
  "abs_price_move": 68.0,
  "favorite_starting_price": 71.0,
  "favorite_ending_price": 1.0,
  "underdog_starting_price": 31.0,
  "underdog_ending_price": 99.0,
  "favorite_price_move": -70.0,
  "underdog_price_move": 68.0,
  "price_expansion": false,
  "price_contraction": true,
  "png_file": "png charts/0031cv.png"
}