{
  "id": "0032af",
  "source_workbook": "kalshi-price-history-kxatpchallengermatch-26feb16butgee-minute.xlsx",
  "event_ticker": "KXATPCHALLENGERMATCH-26FEB16BUTGEE",
  "kalshi_date": "2026-02-16",
  "player_name": "Michael Geerts",
  "opponent_name": "Edas Butvilas",
  "player_side": "dog",
  "match_winner": "Michael Geerts",
  "final_score": "6-3 7-5",
  "starting_price": 32.0,
  "ending_price": 99.0,
  "min_price": 31.0,
  "max_price": 99.0,
  "opponent_starting_price": 70.0,
  "opponent_ending_price": 1.0,
  "row_count": 153,
  "trimmed_opening_rows": 1,
  "trimmed_ending_rows": 4,
  "start_timestamp": "2026-02-15T23:58:00+00:00",
  "end_timestamp": "2026-02-16T09:58:00+00:00",
  "files": {
    "csv": "0032af.csv",
    "json": "0032af.json",
    "npy": "0032af.npy"
  },
  "tags": [
    "2_sets",
    "crossed_40",
    "crossed_50",
    "crossed_60",
    "crossed_70",
    "crossed_75",
    "crossed_80",
    "crossed_90",
    "ending_bucket_90_99",
    "ending_price_0099",
    "first_set_winner",
    "highly_oscillating_shape",
    "huge_range",
    "large_range",
    "many_reversals",
    "medium_single_move",
    "medium_volatility",
    "middle_cross_50",
    "multi_crossed_60",
    "multi_crossed_70",
    "no_tiebreaker",
    "opponent_edas_butvilas",
    "player_michael_geerts",
    "resolved_near_100",
    "second_set_winner",
    "set_1_no_tiebreaker",
    "set_2_no_tiebreaker",
    "starting_bucket_30_39",
    "starting_price_0032",
    "straight_sets",
    "third_set_unknown",
    "underdog",
    "uptrend_finish",
    "winner"
  ],
  "volatility_score": 1.47,
  "max_single_move": 12.18,
  "direction_flips": 34,
  "range_points": 68.0,
  "crossings_25": 0,
  "crossings_50": 1,
  "crossings_75": 2,
  "first_cross_50_pct": 50.0
}