{
  "id": "0034dk",
  "source_workbook": "kalshi-price-history-kxatpmatch-26feb25atmjod-minute.xlsx",
  "event_ticker": "KXATPMATCH-26FEB25ATMJOD",
  "kalshi_date": "2026-02-25",
  "player_name": "Terence Atmane",
  "opponent_name": "Rafael Jodar",
  "player_side": "dog",
  "match_winner": "Terence Atmane",
  "final_score": "6-2 4-6 6-1",
  "starting_price": 34.0,
  "ending_price": 99.0,
  "min_price": 30.0,
  "max_price": 99.0,
  "opponent_starting_price": 68.0,
  "opponent_ending_price": 1.0,
  "row_count": 254,
  "trimmed_opening_rows": 1,
  "trimmed_ending_rows": 3,
  "start_timestamp": "2026-02-25T12:22:00+00:00",
  "end_timestamp": "2026-02-26T01:49:00+00:00",
  "files": {
    "csv": "0034dk.csv",
    "json": "0034dk.json",
    "npy": "0034dk.npy",
    "png": "png charts/0034dk.png"
  },
  "tags": [
    "3_sets",
    "crossed_30",
    "crossed_40",
    "crossed_50",
    "crossed_60",
    "crossed_70",
    "crossed_75",
    "crossed_80",
    "crossed_90",
    "ending_bucket_90_99",
    "ending_price_0099",
    "first_set_winner",
    "highly_oscillating_shape",
    "huge_range",
    "large_range",
    "large_single_move",
    "many_reversals",
    "medium_volatility",
    "middle_cross_50",
    "multi_crossed_30",
    "multi_crossed_40",
    "multi_crossed_50",
    "multi_crossed_60",
    "multi_crossed_70",
    "multi_crossed_75",
    "no_tiebreaker",
    "opponent_rafael_jodar",
    "player_terence_atmane",
    "resolved_near_100",
    "second_set_loser",
    "set_1_no_tiebreaker",
    "set_2_no_tiebreaker",
    "set_3_no_tiebreaker",
    "starting_bucket_30_39",
    "starting_price_0034",
    "third_set_winner",
    "three_set_match",
    "underdog",
    "uptrend_finish",
    "winner",
    "price_move_up",
    "positive_price_move",
    "price_move_up_10",
    "move_up_10",
    "plus_10_up",
    "price_move_up_20",
    "move_up_20",
    "plus_20_up",
    "price_move_up_30",
    "move_up_30",
    "plus_30_up",
    "price_move_up_40",
    "move_up_40",
    "plus_40_up",
    "price_move_up_50",
    "move_up_50",
    "plus_50_up",
    "price_move_up_60",
    "move_up_60",
    "plus_60_up",
    "price_contraction",
    "favorite_down_underdog_up"
  ],
  "volatility_score": 1.1799,
  "max_single_move": 17.48,
  "direction_flips": 29,
  "range_points": 69.0,
  "crossings_25": 0,
  "crossings_50": 7,
  "crossings_75": 3,
  "first_cross_50_pct": 62.85,
  "price_move": 65.0,
  "abs_price_move": 65.0,
  "favorite_starting_price": 68.0,
  "favorite_ending_price": 1.0,
  "underdog_starting_price": 34.0,
  "underdog_ending_price": 99.0,
  "favorite_price_move": -67.0,
  "underdog_price_move": 65.0,
  "price_expansion": false,
  "price_contraction": true,
  "png_file": "png charts/0034dk.png"
}