{
  "id": "0036eb",
  "source_workbook": "kalshi-price-history-kxatpmatch-26jan03sonsak-minute.xlsx",
  "event_ticker": "KXATPMATCH-26JAN03SONSAK",
  "kalshi_date": "2026-01-03",
  "player_name": "Rei Sakamoto",
  "opponent_name": "Lorenzo Sonego",
  "player_side": "dog",
  "match_winner": "Lorenzo Sonego",
  "final_score": "6-2 7-6(4)",
  "starting_price": 36.0,
  "ending_price": 1.36,
  "min_price": 1.09,
  "max_price": 42.54,
  "opponent_starting_price": 67.0,
  "opponent_ending_price": 99.0,
  "row_count": 141,
  "trimmed_opening_rows": 7,
  "trimmed_ending_rows": 3,
  "start_timestamp": "2026-01-06T03:41:00+00:00",
  "end_timestamp": "2026-01-06T07:27:00+00:00",
  "files": {
    "csv": "0036eb.csv",
    "json": "0036eb.json",
    "npy": "0036eb.npy"
  },
  "tags": [
    "2_sets",
    "crossed_10",
    "crossed_20",
    "crossed_25",
    "crossed_30",
    "crossed_40",
    "downtrend_finish",
    "ending_bucket_00_09",
    "ending_price_0001",
    "first_set_loser",
    "highly_oscillating_shape",
    "large_range",
    "loser",
    "many_reversals",
    "medium_range",
    "medium_single_move",
    "medium_volatility",
    "multi_crossed_10",
    "multi_crossed_20",
    "never_crossed_50",
    "opponent_lorenzo_sonego",
    "player_rei_sakamoto",
    "resolved_near_0",
    "second_set_loser",
    "set_1_no_tiebreaker",
    "set_2_tiebreaker",
    "starting_bucket_30_39",
    "starting_price_0036",
    "straight_sets",
    "third_set_unknown",
    "tiebreaker",
    "underdog"
  ],
  "volatility_score": 1.4369,
  "max_single_move": 11.79,
  "direction_flips": 32,
  "range_points": 41.45,
  "crossings_25": 1,
  "crossings_50": 0,
  "crossings_75": 0,
  "first_cross_50_pct": ""
}