{
  "id": "0037cj",
  "source_workbook": "kalshi-price-history-kxatpmatch-25jul27ofnope-minute.xlsx",
  "event_ticker": "KXATPMATCH-25JUL27OFNOPE",
  "kalshi_date": "2025-07-27",
  "player_name": "Sebastian Ofner",
  "opponent_name": "Reilly Opelka",
  "player_side": "dog",
  "match_winner": "Reilly Opelka",
  "final_score": "7-6(6) 7-5",
  "starting_price": 37.0,
  "ending_price": 1.0,
  "min_price": 1.0,
  "max_price": 46.6,
  "opponent_starting_price": 65.0,
  "opponent_ending_price": 99.0,
  "row_count": 138,
  "trimmed_opening_rows": 0,
  "trimmed_ending_rows": 0,
  "start_timestamp": "2025-07-27T14:54:00+00:00",
  "end_timestamp": "2025-07-27T18:35:00+00:00",
  "files": {
    "csv": "0037cj.csv",
    "json": "0037cj.json",
    "npy": "0037cj.npy"
  },
  "tags": [
    "2_sets",
    "crossed_10",
    "crossed_20",
    "crossed_25",
    "crossed_30",
    "crossed_40",
    "downtrend_finish",
    "ending_bucket_00_09",
    "ending_price_0001",
    "first_set_loser",
    "high_volatility",
    "highly_oscillating_shape",
    "large_range",
    "loser",
    "many_reversals",
    "medium_range",
    "medium_single_move",
    "multi_crossed_10",
    "multi_crossed_20",
    "multi_crossed_25",
    "multi_crossed_30",
    "multi_crossed_40",
    "never_crossed_50",
    "opponent_reilly_opelka",
    "player_sebastian_ofner",
    "resolved_near_0",
    "second_set_loser",
    "set_1_tiebreaker",
    "set_2_no_tiebreaker",
    "starting_bucket_30_39",
    "starting_price_0037",
    "straight_sets",
    "third_set_unknown",
    "tiebreaker",
    "underdog"
  ],
  "volatility_score": 2.5886,
  "max_single_move": 11.59,
  "direction_flips": 54,
  "range_points": 45.6,
  "crossings_25": 11,
  "crossings_50": 0,
  "crossings_75": 0,
  "first_cross_50_pct": ""
}