{
  "id": "0038bh",
  "source_workbook": "kalshi-price-history-kxatpchallengermatch-26mar24mccila-minute.xlsx",
  "event_ticker": "KXATPCHALLENGERMATCH-26MAR24MCCILA",
  "kalshi_date": "2026-03-24",
  "player_name": "Andre Ilagan",
  "opponent_name": "James McCabe",
  "player_side": "fav",
  "match_winner": "James McCabe",
  "final_score": "6-4 7-6(9)",
  "starting_price": 38.0,
  "ending_price": 1.0,
  "min_price": 1.0,
  "max_price": 50.31,
  "opponent_starting_price": 66.0,
  "opponent_ending_price": 99.0,
  "row_count": 196,
  "trimmed_opening_rows": 2,
  "trimmed_ending_rows": 1,
  "start_timestamp": "2026-03-24T05:23:00+00:00",
  "end_timestamp": "2026-03-24T10:27:00+00:00",
  "files": {
    "csv": "0038bh.csv",
    "json": "0038bh.json",
    "npy": "0038bh.npy",
    "png": "png charts/0038bh.png"
  },
  "tags": [
    "2_sets",
    "crossed_10",
    "crossed_20",
    "crossed_25",
    "crossed_30",
    "crossed_40",
    "crossed_50",
    "downtrend_finish",
    "ending_bucket_00_09",
    "ending_price_0001",
    "first_set_loser",
    "highly_oscillating_shape",
    "large_range",
    "large_single_move",
    "late_cross_50",
    "loser",
    "many_reversals",
    "medium_range",
    "medium_volatility",
    "multi_crossed_10",
    "multi_crossed_20",
    "multi_crossed_25",
    "multi_crossed_30",
    "multi_crossed_40",
    "opponent_james_mccabe",
    "player_andre_ilagan",
    "resolved_near_0",
    "second_set_loser",
    "set_1_no_tiebreaker",
    "set_2_tiebreaker",
    "starting_bucket_30_39",
    "starting_price_0038",
    "straight_sets",
    "third_set_unknown",
    "tiebreaker",
    "underdog",
    "price_move_down",
    "negative_price_move",
    "price_move_down_10",
    "move_down_10",
    "minus_10_down",
    "price_move_down_20",
    "move_down_20",
    "minus_20_down",
    "price_move_down_30",
    "move_down_30",
    "minus_30_down",
    "price_contraction",
    "favorite_down_underdog_up"
  ],
  "volatility_score": 2.1046,
  "max_single_move": 19.54,
  "direction_flips": 60,
  "range_points": 49.31,
  "crossings_25": 17,
  "crossings_50": 2,
  "crossings_75": 0,
  "first_cross_50_pct": 83.59,
  "price_move": -37.0,
  "abs_price_move": 37.0,
  "favorite_starting_price": 38.0,
  "favorite_ending_price": 1.0,
  "underdog_starting_price": 66.0,
  "underdog_ending_price": 99.0,
  "favorite_price_move": -37.0,
  "underdog_price_move": 33.0,
  "price_expansion": false,
  "price_contraction": true,
  "png_file": "png charts/0038bh.png"
}