{
  "id": "0046bu",
  "source_workbook": "kalshi-price-history-kxatpchallengermatch-26may20dosalc-minute.xlsx",
  "event_ticker": "KXATPCHALLENGERMATCH-26MAY20DOSALC",
  "kalshi_date": "2026-05-20",
  "player_name": "Stefan Dostanic",
  "opponent_name": "Max Alcala Gurri",
  "player_side": "fav",
  "match_winner": "Max Alcala Gurri",
  "final_score": "6-2 6-1",
  "starting_price": 46.0,
  "ending_price": 1.06,
  "min_price": 1.05,
  "max_price": 64.0,
  "opponent_starting_price": 55.0,
  "opponent_ending_price": 99.0,
  "row_count": 90,
  "trimmed_opening_rows": 1,
  "trimmed_ending_rows": 0,
  "start_timestamp": "2026-05-20T03:29:00+00:00",
  "end_timestamp": "2026-05-20T12:48:00+00:00",
  "files": {
    "csv": "0046bu.csv",
    "json": "0046bu.json",
    "npy": "0046bu.npy",
    "png": "png charts/0046bu.png"
  },
  "tags": [
    "2_sets",
    "crossed_10",
    "crossed_20",
    "crossed_25",
    "crossed_30",
    "crossed_40",
    "crossed_50",
    "crossed_60",
    "downtrend_finish",
    "ending_bucket_00_09",
    "ending_price_0001",
    "first_set_loser",
    "highly_oscillating_shape",
    "huge_range",
    "inverted_v_failed_spike",
    "large_range",
    "loser",
    "many_reversals",
    "medium_single_move",
    "medium_volatility",
    "middle_cross_50",
    "multi_crossed_20",
    "multi_crossed_25",
    "multi_crossed_30",
    "no_tiebreaker",
    "opponent_max_alcala_gurri",
    "player_stefan_dostanic",
    "resolved_near_0",
    "second_set_loser",
    "set_1_no_tiebreaker",
    "set_2_no_tiebreaker",
    "slight_underdog",
    "starting_bucket_40_49",
    "starting_price_0046",
    "straight_sets",
    "third_set_unknown",
    "price_move_down",
    "negative_price_move",
    "price_move_down_10",
    "move_down_10",
    "minus_10_down",
    "price_move_down_20",
    "move_down_20",
    "minus_20_down",
    "price_move_down_30",
    "move_down_30",
    "minus_30_down",
    "price_move_down_40",
    "move_down_40",
    "minus_40_down",
    "price_contraction",
    "favorite_down_underdog_up"
  ],
  "volatility_score": 1.6784,
  "max_single_move": 11.0,
  "direction_flips": 24,
  "range_points": 62.95,
  "crossings_25": 5,
  "crossings_50": 2,
  "crossings_75": 0,
  "first_cross_50_pct": 35.96,
  "price_move": -44.94,
  "abs_price_move": 44.94,
  "favorite_starting_price": 46.0,
  "favorite_ending_price": 1.06,
  "underdog_starting_price": 55.0,
  "underdog_ending_price": 99.0,
  "favorite_price_move": -44.94,
  "underdog_price_move": 44.0,
  "price_expansion": false,
  "price_contraction": true,
  "png_file": "png charts/0046bu.png"
}