{
  "id": "0046di",
  "source_workbook": "kalshi-price-history-kxatpmatch-26apr22altcer-minute.xlsx",
  "event_ticker": "KXATPMATCH-26APR22ALTCER",
  "kalshi_date": "2026-04-22",
  "player_name": "Daniel Altmaier",
  "opponent_name": "Juan Manuel Cerundolo",
  "player_side": "fav",
  "match_winner": "Juan Manuel Cerundolo",
  "final_score": "6-4 6-4",
  "starting_price": 46.0,
  "ending_price": 1.0,
  "min_price": 1.0,
  "max_price": 67.99,
  "opponent_starting_price": 55.0,
  "opponent_ending_price": 99.0,
  "row_count": 314,
  "trimmed_opening_rows": 3,
  "trimmed_ending_rows": 2,
  "start_timestamp": "2026-04-23T03:43:00+00:00",
  "end_timestamp": "2026-04-23T16:30:00+00:00",
  "files": {
    "csv": "0046di.csv",
    "json": "0046di.json",
    "npy": "0046di.npy"
  },
  "tags": [
    "2_sets",
    "crossed_10",
    "crossed_20",
    "crossed_25",
    "crossed_30",
    "crossed_40",
    "crossed_50",
    "crossed_60",
    "downtrend_finish",
    "ending_bucket_00_09",
    "ending_price_0001",
    "first_set_loser",
    "highly_oscillating_shape",
    "huge_range",
    "inverted_v_failed_spike",
    "large_range",
    "late_cross_50",
    "loser",
    "low_volatility",
    "many_reversals",
    "medium_single_move",
    "multi_crossed_25",
    "multi_crossed_50",
    "no_tiebreaker",
    "opponent_juan_manuel_cerundolo",
    "player_daniel_altmaier",
    "resolved_near_0",
    "second_set_loser",
    "set_1_no_tiebreaker",
    "set_2_no_tiebreaker",
    "slight_underdog",
    "starting_bucket_40_49",
    "starting_price_0046",
    "straight_sets",
    "third_set_unknown"
  ],
  "volatility_score": 0.611,
  "max_single_move": 9.1,
  "direction_flips": 28,
  "range_points": 66.99,
  "crossings_25": 7,
  "crossings_50": 4,
  "crossings_75": 0,
  "first_cross_50_pct": 77.64
}