{
  "id": "0056dv",
  "source_workbook": "kalshi-price-history-kxatpmatch-26apr24lehtab-minute.xlsx",
  "event_ticker": "KXATPMATCH-26APR24LEHTAB",
  "kalshi_date": "2026-04-24",
  "player_name": "Jiri Lehecka",
  "opponent_name": "Alejandro Tabilo",
  "player_side": "fav",
  "match_winner": "Jiri Lehecka",
  "final_score": "3-6 7-6(3) 6-4",
  "starting_price": 56.0,
  "ending_price": 99.0,
  "min_price": 21.35,
  "max_price": 99.0,
  "opponent_starting_price": 48.84,
  "opponent_ending_price": 1.0,
  "row_count": 386,
  "trimmed_opening_rows": 1,
  "trimmed_ending_rows": 1,
  "start_timestamp": "2026-04-24T04:31:00+00:00",
  "end_timestamp": "2026-04-24T14:41:00+00:00",
  "files": {
    "csv": "0056dv.csv",
    "json": "0056dv.json",
    "npy": "0056dv.npy"
  },
  "tags": [
    "3_sets",
    "crossed_25",
    "crossed_30",
    "crossed_40",
    "crossed_50",
    "crossed_60",
    "crossed_70",
    "crossed_75",
    "crossed_80",
    "crossed_90",
    "drawdown_recovery",
    "early_cross_50",
    "ending_bucket_90_99",
    "ending_price_0099",
    "extreme_range",
    "first_set_loser",
    "highly_oscillating_shape",
    "huge_range",
    "large_single_move",
    "low_volatility",
    "many_reversals",
    "multi_crossed_25",
    "multi_crossed_30",
    "multi_crossed_40",
    "multi_crossed_50",
    "multi_crossed_60",
    "opponent_alejandro_tabilo",
    "player_jiri_lehecka",
    "resolved_near_100",
    "second_set_winner",
    "set_1_no_tiebreaker",
    "set_2_tiebreaker",
    "set_3_no_tiebreaker",
    "slight_favorite",
    "starting_bucket_50_59",
    "starting_price_0056",
    "third_set_winner",
    "three_set_match",
    "tiebreaker",
    "uptrend_finish",
    "v_shape_recovery",
    "winner"
  ],
  "volatility_score": 0.9031,
  "max_single_move": 22.51,
  "direction_flips": 59,
  "range_points": 77.65,
  "crossings_25": 4,
  "crossings_50": 4,
  "crossings_75": 1,
  "first_cross_50_pct": 0.0
}