{
  "id": "0056fa",
  "source_workbook": "kalshi-price-history-kxatpmatch-26mar22jodetc-minute.xlsx",
  "event_ticker": "KXATPMATCH-26MAR22JODETC",
  "kalshi_date": "2026-03-22",
  "player_name": "Rafael Jodar",
  "opponent_name": "Tomas Martin Etcheverry",
  "player_side": "fav",
  "match_winner": "Tomas Martin Etcheverry",
  "final_score": "7-5 6-4",
  "starting_price": 56.0,
  "ending_price": 1.0,
  "min_price": 1.0,
  "max_price": 68.18,
  "opponent_starting_price": 46.0,
  "opponent_ending_price": 99.0,
  "row_count": 375,
  "trimmed_opening_rows": 1,
  "trimmed_ending_rows": 2,
  "start_timestamp": "2026-03-22T06:48:00+00:00",
  "end_timestamp": "2026-03-22T19:54:00+00:00",
  "files": {
    "csv": "0056fa.csv",
    "json": "0056fa.json",
    "npy": "0056fa.npy"
  },
  "tags": [
    "2_sets",
    "crossed_10",
    "crossed_20",
    "crossed_25",
    "crossed_30",
    "crossed_40",
    "crossed_50",
    "crossed_60",
    "downtrend_finish",
    "early_cross_50",
    "ending_bucket_00_09",
    "ending_price_0001",
    "first_set_loser",
    "highly_oscillating_shape",
    "huge_range",
    "large_range",
    "large_single_move",
    "loser",
    "low_volatility",
    "many_reversals",
    "multi_crossed_10",
    "multi_crossed_40",
    "multi_crossed_50",
    "multi_crossed_60",
    "no_tiebreaker",
    "opponent_tomas_martin_etcheverry",
    "player_rafael_jodar",
    "resolved_near_0",
    "second_set_loser",
    "set_1_no_tiebreaker",
    "set_2_no_tiebreaker",
    "slight_favorite",
    "starting_bucket_50_59",
    "starting_price_0056",
    "straight_sets",
    "third_set_unknown"
  ],
  "volatility_score": 0.8058,
  "max_single_move": 16.9,
  "direction_flips": 53,
  "range_points": 67.18,
  "crossings_25": 1,
  "crossings_50": 3,
  "crossings_75": 0,
  "first_cross_50_pct": 0.0
}