{
  "id": "0060bg",
  "source_workbook": "kalshi-price-history-kxatpchallengermatch-26mar20ronrei-minute.xlsx",
  "event_ticker": "KXATPCHALLENGERMATCH-26MAR20RONREI",
  "kalshi_date": "2026-03-20",
  "player_name": "Joao Lucas Reis Da Silva",
  "opponent_name": "Franco Roncadelli",
  "player_side": "fav",
  "match_winner": "Franco Roncadelli",
  "final_score": "4-6 6-1 6-2",
  "starting_price": 60.0,
  "ending_price": 2.37,
  "min_price": 2.02,
  "max_price": 79.0,
  "opponent_starting_price": 42.0,
  "opponent_ending_price": 99.0,
  "row_count": 152,
  "trimmed_opening_rows": 4,
  "trimmed_ending_rows": 0,
  "start_timestamp": "2026-03-20T15:15:00+00:00",
  "end_timestamp": "2026-03-21T01:21:00+00:00",
  "files": {
    "csv": "0060bg.csv",
    "json": "0060bg.json",
    "npy": "0060bg.npy",
    "png": "png charts/0060bg.png"
  },
  "tags": [
    "3_sets",
    "crossed_10",
    "crossed_20",
    "crossed_25",
    "crossed_30",
    "crossed_40",
    "crossed_50",
    "crossed_60",
    "crossed_70",
    "crossed_75",
    "downtrend_finish",
    "early_cross_50",
    "ending_bucket_00_09",
    "ending_price_0002",
    "extreme_range",
    "favorite",
    "first_set_winner",
    "high_volatility",
    "highly_oscillating_shape",
    "huge_range",
    "inverted_v_failed_spike",
    "large_single_move",
    "loser",
    "many_reversals",
    "multi_crossed_20",
    "multi_crossed_25",
    "multi_crossed_30",
    "multi_crossed_40",
    "multi_crossed_50",
    "multi_crossed_60",
    "multi_crossed_70",
    "multi_crossed_75",
    "no_tiebreaker",
    "opponent_franco_roncadelli",
    "player_joao_lucas_reis_da_silva",
    "resolved_near_0",
    "second_set_loser",
    "set_1_no_tiebreaker",
    "set_2_no_tiebreaker",
    "set_3_no_tiebreaker",
    "starting_bucket_60_69",
    "starting_price_0060",
    "third_set_loser",
    "three_set_match",
    "price_move_down",
    "negative_price_move",
    "price_move_down_10",
    "move_down_10",
    "minus_10_down",
    "price_move_down_20",
    "move_down_20",
    "minus_20_down",
    "price_move_down_30",
    "move_down_30",
    "minus_30_down",
    "price_move_down_40",
    "move_down_40",
    "minus_40_down",
    "price_move_down_50",
    "move_down_50",
    "minus_50_down",
    "price_contraction",
    "favorite_down_underdog_up"
  ],
  "volatility_score": 3.0798,
  "max_single_move": 16.49,
  "direction_flips": 50,
  "range_points": 76.98,
  "crossings_25": 5,
  "crossings_50": 11,
  "crossings_75": 6,
  "first_cross_50_pct": 0.0,
  "price_move": -57.63,
  "abs_price_move": 57.63,
  "favorite_starting_price": 60.0,
  "favorite_ending_price": 2.37,
  "underdog_starting_price": 42.0,
  "underdog_ending_price": 99.0,
  "favorite_price_move": -57.63,
  "underdog_price_move": 57.0,
  "price_expansion": false,
  "price_contraction": true,
  "png_file": "png charts/0060bg.png"
}