{
  "id": "0061bb",
  "source_workbook": "kalshi-price-history-kxatpchallengermatch-26mar10baxneu-minute.xlsx",
  "event_ticker": "KXATPCHALLENGERMATCH-26MAR10BAXNEU",
  "kalshi_date": "2026-03-10",
  "player_name": "Florent Bax",
  "opponent_name": "Maximilian Neuchrist",
  "player_side": "fav",
  "match_winner": "Maximilian Neuchrist",
  "final_score": "7-6(5) 6-7(4) 7-6(6)",
  "starting_price": 61.0,
  "ending_price": 1.0,
  "min_price": 1.0,
  "max_price": 88.7,
  "opponent_starting_price": 40.0,
  "opponent_ending_price": 99.0,
  "row_count": 172,
  "trimmed_opening_rows": 1,
  "trimmed_ending_rows": 0,
  "start_timestamp": "2026-03-10T10:00:00+00:00",
  "end_timestamp": "2026-03-10T15:42:00+00:00",
  "files": {
    "csv": "0061bb.csv",
    "json": "0061bb.json",
    "npy": "0061bb.npy"
  },
  "tags": [
    "3_sets",
    "crossed_10",
    "crossed_20",
    "crossed_25",
    "crossed_30",
    "crossed_40",
    "crossed_50",
    "crossed_60",
    "crossed_70",
    "crossed_75",
    "crossed_80",
    "downtrend_finish",
    "early_cross_50",
    "ending_bucket_00_09",
    "ending_price_0001",
    "extreme_range",
    "failed_spike",
    "favorite",
    "first_set_loser",
    "high_volatility",
    "highly_oscillating_shape",
    "huge_range",
    "huge_single_move",
    "inverted_v_failed_spike",
    "loser",
    "many_reversals",
    "multi_crossed_20",
    "multi_crossed_25",
    "multi_crossed_30",
    "multi_crossed_40",
    "multi_crossed_50",
    "multi_crossed_60",
    "multi_crossed_70",
    "multi_crossed_75",
    "multi_crossed_80",
    "opponent_maximilian_neuchrist",
    "player_florent_bax",
    "resolved_near_0",
    "second_set_winner",
    "set_1_tiebreaker",
    "set_2_tiebreaker",
    "set_3_tiebreaker",
    "starting_bucket_60_69",
    "starting_price_0061",
    "third_set_loser",
    "three_set_match",
    "tiebreaker"
  ],
  "volatility_score": 3.9297,
  "max_single_move": 38.87,
  "direction_flips": 65,
  "range_points": 87.7,
  "crossings_25": 9,
  "crossings_50": 7,
  "crossings_75": 6,
  "first_cross_50_pct": 0.0
}