{
  "id": "0061t",
  "source_workbook": "kalshi-price-history-kxatpchallengermatch-26apr28artbic-minute.xlsx",
  "event_ticker": "KXATPCHALLENGERMATCH-26APR28ARTBIC",
  "kalshi_date": "2026-04-28",
  "player_name": "Blaise Bicknell",
  "opponent_name": "Bor Artnak",
  "player_side": "dog",
  "match_winner": "Blaise Bicknell",
  "final_score": "4-3 RET",
  "starting_price": 61.0,
  "ending_price": 89.71,
  "min_price": 31.77,
  "max_price": 89.71,
  "opponent_starting_price": 40.0,
  "opponent_ending_price": 7.89,
  "row_count": 40,
  "trimmed_opening_rows": 8,
  "trimmed_ending_rows": 0,
  "start_timestamp": "2026-04-28T18:44:00+00:00",
  "end_timestamp": "2026-04-28T20:12:00+00:00",
  "files": {
    "csv": "0061t.csv",
    "json": "0061t.json",
    "npy": "0061t.npy"
  },
  "tags": [
    "1_sets",
    "crossed_40",
    "crossed_50",
    "crossed_60",
    "crossed_70",
    "crossed_75",
    "crossed_80",
    "drawdown_recovery",
    "early_cross_50",
    "ending_bucket_90_99",
    "ending_price_0090",
    "favorite",
    "first_set_winner",
    "large_range",
    "large_single_move",
    "moderate_reversals",
    "multi_crossed_40",
    "multi_crossed_50",
    "multi_crossed_60",
    "no_tiebreaker",
    "opponent_bor_artnak",
    "oscillating_shape",
    "player_blaise_bicknell",
    "second_set_unknown",
    "set_1_no_tiebreaker",
    "starting_bucket_60_69",
    "starting_price_0061",
    "third_set_unknown",
    "uptrend_finish",
    "v_shape_recovery",
    "very_high_volatility",
    "winner"
  ],
  "volatility_score": 4.0187,
  "max_single_move": 16.15,
  "direction_flips": 10,
  "range_points": 57.94,
  "crossings_25": 0,
  "crossings_50": 4,
  "crossings_75": 1,
  "first_cross_50_pct": 0.0
}