{
  "id": "0065bb",
  "source_workbook": "kalshi-price-history-kxatpchallengermatch-26mar12mensai-minute.xlsx",
  "event_ticker": "KXATPCHALLENGERMATCH-26MAR12MENSAI",
  "kalshi_date": "2026-03-12",
  "player_name": "Facundo Mena",
  "opponent_name": "Nikolas Sanchez Izquierdo",
  "player_side": "fav",
  "match_winner": "Nikolas Sanchez Izquierdo",
  "final_score": "7-6(3) 6-4",
  "starting_price": 65.0,
  "ending_price": 4.41,
  "min_price": 2.63,
  "max_price": 73.0,
  "opponent_starting_price": 39.0,
  "opponent_ending_price": 99.0,
  "row_count": 171,
  "trimmed_opening_rows": 0,
  "trimmed_ending_rows": 2,
  "start_timestamp": "2026-03-12T06:12:00+00:00",
  "end_timestamp": "2026-03-12T18:20:00+00:00",
  "files": {
    "csv": "0065bb.csv",
    "json": "0065bb.json",
    "npy": "0065bb.npy"
  },
  "tags": [
    "2_sets",
    "crossed_10",
    "crossed_20",
    "crossed_25",
    "crossed_30",
    "crossed_40",
    "crossed_50",
    "crossed_60",
    "crossed_70",
    "downtrend_finish",
    "early_cross_50",
    "ending_bucket_00_09",
    "ending_price_0004",
    "extreme_range",
    "favorite",
    "first_set_loser",
    "high_volatility",
    "highly_oscillating_shape",
    "huge_range",
    "large_single_move",
    "loser",
    "many_reversals",
    "multi_crossed_10",
    "multi_crossed_20",
    "multi_crossed_25",
    "multi_crossed_40",
    "multi_crossed_50",
    "multi_crossed_60",
    "multi_crossed_70",
    "opponent_nikolas_sanchez_izquierdo",
    "player_facundo_mena",
    "resolved_near_0",
    "second_set_loser",
    "set_1_tiebreaker",
    "set_2_no_tiebreaker",
    "starting_bucket_60_69",
    "starting_price_0065",
    "straight_sets",
    "third_set_unknown",
    "tiebreaker"
  ],
  "volatility_score": 2.9125,
  "max_single_move": 15.05,
  "direction_flips": 69,
  "range_points": 70.37,
  "crossings_25": 3,
  "crossings_50": 7,
  "crossings_75": 0,
  "first_cross_50_pct": 0.0
}