{
  "id": "0066f",
  "source_workbook": "kalshi-price-history-kxatpchallengermatch-26apr11jarrod-minute.xlsx",
  "event_ticker": "KXATPCHALLENGERMATCH-26APR11JARROD",
  "kalshi_date": "2026-04-11",
  "player_name": "Nicolas Jarry",
  "opponent_name": "Jurij Rodionov",
  "player_side": "dog",
  "match_winner": "Jurij Rodionov",
  "final_score": "6-7(6) 7-6(4) 7-6(4)",
  "starting_price": 66.0,
  "ending_price": 1.0,
  "min_price": 1.0,
  "max_price": 89.97,
  "opponent_starting_price": 36.0,
  "opponent_ending_price": 99.0,
  "row_count": 266,
  "trimmed_opening_rows": 1,
  "trimmed_ending_rows": 1,
  "start_timestamp": "2026-04-11T04:45:00+00:00",
  "end_timestamp": "2026-04-11T18:32:00+00:00",
  "files": {
    "csv": "0066f.csv",
    "json": "0066f.json",
    "npy": "0066f.npy"
  },
  "tags": [
    "3_sets",
    "crossed_10",
    "crossed_20",
    "crossed_25",
    "crossed_30",
    "crossed_40",
    "crossed_50",
    "crossed_60",
    "crossed_70",
    "crossed_75",
    "crossed_80",
    "downtrend_finish",
    "early_cross_50",
    "ending_bucket_00_09",
    "ending_price_0001",
    "extreme_range",
    "favorite",
    "first_set_winner",
    "highly_oscillating_shape",
    "huge_range",
    "inverted_v_failed_spike",
    "large_single_move",
    "loser",
    "many_reversals",
    "medium_volatility",
    "multi_crossed_20",
    "multi_crossed_25",
    "multi_crossed_50",
    "multi_crossed_60",
    "multi_crossed_70",
    "multi_crossed_75",
    "multi_crossed_80",
    "opponent_jurij_rodionov",
    "player_nicolas_jarry",
    "resolved_near_0",
    "second_set_loser",
    "set_1_tiebreaker",
    "set_2_tiebreaker",
    "set_3_tiebreaker",
    "starting_bucket_60_69",
    "starting_price_0066",
    "third_set_loser",
    "three_set_match",
    "tiebreaker"
  ],
  "volatility_score": 2.4434,
  "max_single_move": 16.98,
  "direction_flips": 84,
  "range_points": 88.97,
  "crossings_25": 3,
  "crossings_50": 5,
  "crossings_75": 16,
  "first_cross_50_pct": 0.0
}