{
  "id": "0072ap",
  "source_workbook": "kalshi-price-history-kxatpchallengermatch-26mar24hsubou-minute.xlsx",
  "event_ticker": "KXATPCHALLENGERMATCH-26MAR24HSUBOU",
  "kalshi_date": "2026-03-24",
  "player_name": "Yu Hsiou Hsu",
  "opponent_name": "Justin Boulais",
  "player_side": "dog",
  "match_winner": "Yu Hsiou Hsu",
  "final_score": "7-5 6-3",
  "starting_price": 72.0,
  "ending_price": 99.0,
  "min_price": 38.64,
  "max_price": 99.0,
  "opponent_starting_price": 32.0,
  "opponent_ending_price": 1.0,
  "row_count": 223,
  "trimmed_opening_rows": 0,
  "trimmed_ending_rows": 4,
  "start_timestamp": "2026-03-23T21:10:00+00:00",
  "end_timestamp": "2026-03-24T08:19:00+00:00",
  "files": {
    "csv": "0072ap.csv",
    "json": "0072ap.json",
    "npy": "0072ap.npy",
    "png": "png charts/0072ap.png"
  },
  "tags": [
    "2_sets",
    "crossed_40",
    "crossed_50",
    "crossed_60",
    "crossed_70",
    "crossed_75",
    "crossed_80",
    "crossed_90",
    "drawdown_recovery",
    "early_cross_50",
    "ending_bucket_90_99",
    "ending_price_0099",
    "favorite",
    "first_set_winner",
    "highly_oscillating_shape",
    "huge_range",
    "large_range",
    "many_reversals",
    "medium_single_move",
    "medium_volatility",
    "multi_crossed_50",
    "multi_crossed_60",
    "multi_crossed_70",
    "multi_crossed_90",
    "no_tiebreaker",
    "opponent_justin_boulais",
    "player_yu_hsiou_hsu",
    "resolved_near_100",
    "second_set_winner",
    "set_1_no_tiebreaker",
    "set_2_no_tiebreaker",
    "starting_bucket_70_79",
    "starting_price_0072",
    "straight_sets",
    "third_set_unknown",
    "uptrend_finish",
    "v_shape_recovery",
    "winner",
    "price_move_up",
    "positive_price_move",
    "price_move_up_10",
    "move_up_10",
    "plus_10_up",
    "price_move_up_20",
    "move_up_20",
    "plus_20_up",
    "price_contraction",
    "favorite_down_underdog_up"
  ],
  "volatility_score": 1.6586,
  "max_single_move": 13.1,
  "direction_flips": 50,
  "range_points": 60.36,
  "crossings_25": 0,
  "crossings_50": 6,
  "crossings_75": 1,
  "first_cross_50_pct": 0.0,
  "price_move": 27.0,
  "abs_price_move": 27.0,
  "favorite_starting_price": 32.0,
  "favorite_ending_price": 1.0,
  "underdog_starting_price": 72.0,
  "underdog_ending_price": 99.0,
  "favorite_price_move": -31.0,
  "underdog_price_move": 27.0,
  "price_expansion": false,
  "price_contraction": true,
  "png_file": "png charts/0072ap.png"
}