{
  "id": "0075al",
  "source_workbook": "kalshi-price-history-kxatpchallengermatch-26jun05molsac-minute.xlsx",
  "event_ticker": "KXATPCHALLENGERMATCH-26JUN05MOLSAC",
  "kalshi_date": "2026-06-05",
  "player_name": "Alex Molcan",
  "opponent_name": "Vitaliy Sachko",
  "player_side": "fav",
  "match_winner": "Alex Molcan",
  "final_score": "3-6 6-1 6-4",
  "starting_price": 75.0,
  "ending_price": 99.0,
  "min_price": 37.1,
  "max_price": 99.0,
  "opponent_starting_price": 26.0,
  "opponent_ending_price": 1.0,
  "row_count": 252,
  "trimmed_opening_rows": 1,
  "trimmed_ending_rows": 3,
  "start_timestamp": "2026-06-04T23:41:00+00:00",
  "end_timestamp": "2026-06-05T12:24:00+00:00",
  "files": {
    "csv": "0075al.csv",
    "json": "0075al.json",
    "npy": "0075al.npy"
  },
  "tags": [
    "3_sets",
    "crossed_40",
    "crossed_50",
    "crossed_60",
    "crossed_70",
    "crossed_75",
    "crossed_80",
    "crossed_90",
    "drawdown_recovery",
    "early_cross_50",
    "ending_bucket_90_99",
    "ending_price_0099",
    "first_set_loser",
    "heavy_favorite",
    "highly_oscillating_shape",
    "huge_range",
    "large_range",
    "many_reversals",
    "medium_single_move",
    "medium_volatility",
    "multi_crossed_50",
    "multi_crossed_70",
    "multi_crossed_75",
    "multi_crossed_80",
    "multi_crossed_90",
    "no_tiebreaker",
    "opponent_vitaliy_sachko",
    "player_alex_molcan",
    "resolved_near_100",
    "second_set_winner",
    "set_1_no_tiebreaker",
    "set_2_no_tiebreaker",
    "set_3_no_tiebreaker",
    "starting_bucket_70_79",
    "starting_price_0075",
    "third_set_winner",
    "three_set_match",
    "uptrend_finish",
    "v_shape_recovery",
    "winner"
  ],
  "volatility_score": 1.4492,
  "max_single_move": 14.97,
  "direction_flips": 54,
  "range_points": 61.9,
  "crossings_25": 0,
  "crossings_50": 4,
  "crossings_75": 18,
  "first_cross_50_pct": 0.0
}