{
  "id": "0096aa",
  "source_workbook": "kalshi-price-history-kxatpmatch-26mar06alcdim-minute.xlsx",
  "event_ticker": "KXATPMATCH-26MAR06ALCDIM",
  "kalshi_date": "2026-03-06",
  "player_name": "Carlos Alcaraz",
  "opponent_name": "Grigor Dimitrov",
  "player_side": "fav",
  "match_winner": "Carlos Alcaraz",
  "final_score": "6-2 6-3",
  "starting_price": 96.0,
  "ending_price": 99.0,
  "min_price": 93.0,
  "max_price": 99.0,
  "opponent_starting_price": 5.0,
  "opponent_ending_price": 1.0,
  "row_count": 337,
  "trimmed_opening_rows": 2,
  "trimmed_ending_rows": 2,
  "start_timestamp": "2026-03-07T13:21:00+00:00",
  "end_timestamp": "2026-03-08T01:34:00+00:00",
  "files": {
    "csv": "0096aa.csv",
    "json": "0096aa.json",
    "npy": "0096aa.npy"
  },
  "tags": [
    "2_sets",
    "early_cross_50",
    "ending_bucket_90_99",
    "ending_price_0099",
    "first_set_winner",
    "heavy_favorite",
    "highly_oscillating_shape",
    "low_volatility",
    "many_reversals",
    "no_tiebreaker",
    "opponent_grigor_dimitrov",
    "player_carlos_alcaraz",
    "resolved_near_100",
    "second_set_winner",
    "set_1_no_tiebreaker",
    "set_2_no_tiebreaker",
    "sideways_finish",
    "small_range",
    "small_single_move",
    "starting_bucket_90_99",
    "starting_price_0096",
    "straight_sets",
    "third_set_unknown",
    "winner"
  ],
  "volatility_score": 0.1733,
  "max_single_move": 3.01,
  "direction_flips": 22,
  "range_points": 6.0,
  "crossings_25": 0,
  "crossings_50": 0,
  "crossings_75": 0,
  "first_cross_50_pct": 0.0
}